limma_py/__init__.py
limma_py/contrasts.py
limma_py/ebayes.py
limma_py/fitFDist.py
limma_py/lmfit.py
limma_py/makeContrasts.py
limma_py/squeezeVar.py
limma_py/test_functions.py
limma_py/toptable.py
limma_py/utils/__init__.py
limma_py/utils/ns.py
limma_py-0.1.0.dist-info/licenses/LICENSE
limma_py-0.1.0.dist-info/METADATA
limma_py-0.1.0.dist-info/WHEEL
limma_py-0.1.0.dist-info/top_level.txt
limma_py-0.1.0.dist-info/RECORD
