Metadata-Version: 2.4
Name: limma_py
Version: 0.1.0
Summary: Python implementation of R's limma package for differential expression analysis
Home-page: https://github.com/wd1566/limma-py
Author: Zhang Xian
Author-email: Zhang Xian <2967569628@qq.com>
License: MIT
Project-URL: Homepage, https://github.com/wd1566/limma_py
Project-URL: Repository, https://github.com/wd1566/limma_py
Project-URL: Issues, https://github.com/wd1566/limma_py/issues
Keywords: bioinformatics,limma,differential-expression,genomics
Classifier: Development Status :: 3 - Alpha
Classifier: Intended Audience :: Science/Research
Classifier: License :: OSI Approved :: MIT License
Classifier: Operating System :: OS Independent
Classifier: Programming Language :: Python :: 3
Classifier: Programming Language :: Python :: 3.7
Classifier: Programming Language :: Python :: 3.8
Classifier: Programming Language :: Python :: 3.9
Classifier: Programming Language :: Python :: 3.10
Classifier: Programming Language :: Python :: 3.11
Classifier: Topic :: Scientific/Engineering :: Bio-Informatics
Requires-Python: >=3.7
License-File: LICENSE
Requires-Dist: numpy>=1.19.0
Requires-Dist: pandas>=1.3.0
Requires-Dist: scipy>=1.7.0
Requires-Dist: statsmodels>=0.13.0
Dynamic: license-file
